{
    "repairs": [],
    "executionInfo": {
        "soraldVersion": "commit: 0c75eb6f",
        "javaVersion": "11.0.8",
        "originalArgs": [
            "repair",
            "--file-output-strategy",
            "IN_PLACE",
            "--original-files-path",
            "./",
            "--rule-keys",
            "2111",
            "--stats-output-file",
            "repair.json"
        ]
    },
    "totalTimeMs": 2754,
    "repairTimeMs": 164,
    "startTimeMs": 1610918269117,
    "crashes": [],
    "endTimeMs": 1610918271871,
    "parseTimeMs": 980
}