{
    "repairs": [],
    "executionInfo": {
        "soraldVersion": "commit: ad3fdd7c",
        "javaVersion": "11.0.8",
        "originalArgs": [
            "repair",
            "--file-output-strategy",
            "IN_PLACE",
            "--original-files-path",
            "./",
            "--rule-keys",
            "2142",
            "--stats-output-file",
            "repair.json"
        ]
    },
    "totalTimeMs": 3515,
    "repairTimeMs": 175,
    "startTimeMs": 1612818656253,
    "crashes": [],
    "endTimeMs": 1612818659768,
    "parseTimeMs": 1364
}