{
    "repairs": [],
    "executionInfo": {
        "soraldVersion": "commit: 0c75eb6f",
        "javaVersion": "11.0.8",
        "originalArgs": [
            "repair",
            "--file-output-strategy",
            "IN_PLACE",
            "--original-files-path",
            "./",
            "--rule-keys",
            "4973",
            "--stats-output-file",
            "repair.json"
        ]
    },
    "totalTimeMs": 2865,
    "repairTimeMs": 167,
    "startTimeMs": 1610903593643,
    "crashes": [],
    "endTimeMs": 1610903596508,
    "parseTimeMs": 964
}