{
    "repairs": [],
    "executionInfo": {
        "soraldVersion": "commit: ad3fdd7c",
        "javaVersion": "11.0.8",
        "originalArgs": [
            "repair",
            "--file-output-strategy",
            "IN_PLACE",
            "--original-files-path",
            "./",
            "--rule-keys",
            "2095",
            "--stats-output-file",
            "repair.json"
        ]
    },
    "totalTimeMs": 10123,
    "repairTimeMs": 173,
    "startTimeMs": 1612803164036,
    "crashes": [],
    "endTimeMs": 1612803174159,
    "parseTimeMs": 2781
}