{
    "repairs": [],
    "executionInfo": {
        "soraldVersion": "commit: 9a05e51b",
        "javaVersion": "11.0.8",
        "originalArgs": [
            "repair",
            "--file-output-strategy",
            "IN_PLACE",
            "--original-files-path",
            "./",
            "--rule-keys",
            "2272",
            "--stats-output-file",
            "repair.json"
        ]
    },
    "totalTimeMs": 1598,
    "repairTimeMs": 140,
    "startTimeMs": 1611606104159,
    "crashes": [],
    "endTimeMs": 1611606105757,
    "parseTimeMs": 377
}