{
    "repairs": [],
    "executionInfo": {
        "soraldVersion": "commit: 38248282",
        "javaVersion": "11.0.8",
        "originalArgs": [
            "repair",
            "--file-output-strategy",
            "IN_PLACE",
            "--original-files-path",
            "./",
            "--rule-keys",
            "2095",
            "--stats-output-file",
            "repair.json"
        ]
    },
    "totalTimeMs": 8943,
    "repairTimeMs": 213,
    "startTimeMs": 1613355271451,
    "crashes": [],
    "endTimeMs": 1613355280394,
    "parseTimeMs": 3023
}