{
    "repairs": [],
    "executionInfo": {
        "soraldVersion": "commit: 9a05e51b",
        "javaVersion": "11.0.8",
        "originalArgs": [
            "repair",
            "--file-output-strategy",
            "IN_PLACE",
            "--original-files-path",
            "./",
            "--rule-keys",
            "2111",
            "--stats-output-file",
            "repair.json"
        ]
    },
    "totalTimeMs": 5793,
    "repairTimeMs": 277,
    "startTimeMs": 1611607722171,
    "crashes": [],
    "endTimeMs": 1611607727964,
    "parseTimeMs": 2136
}