{
    "repairs": [],
    "executionInfo": {
        "soraldVersion": "commit: ad3fdd7c",
        "javaVersion": "11.0.8",
        "originalArgs": [
            "repair",
            "--file-output-strategy",
            "IN_PLACE",
            "--original-files-path",
            "./",
            "--rule-keys",
            "2225",
            "--stats-output-file",
            "repair.json"
        ]
    },
    "totalTimeMs": 4033,
    "repairTimeMs": 202,
    "startTimeMs": 1612810072531,
    "crashes": [],
    "endTimeMs": 1612810076564,
    "parseTimeMs": 1400
}