{
    "repairs": [],
    "executionInfo": {
        "soraldVersion": "commit: ad3fdd7c",
        "javaVersion": "11.0.8",
        "originalArgs": [
            "repair",
            "--file-output-strategy",
            "IN_PLACE",
            "--original-files-path",
            "./",
            "--rule-keys",
            "2225",
            "--stats-output-file",
            "repair.json"
        ]
    },
    "totalTimeMs": 18951,
    "repairTimeMs": 828,
    "startTimeMs": 1612808301578,
    "crashes": [],
    "endTimeMs": 1612808320529,
    "parseTimeMs": 8694
}