{
    "repairs": [],
    "executionInfo": {
        "soraldVersion": "commit: 38248282",
        "javaVersion": "11.0.8",
        "originalArgs": [
            "repair",
            "--file-output-strategy",
            "IN_PLACE",
            "--original-files-path",
            "./",
            "--rule-keys",
            "2272",
            "--stats-output-file",
            "repair.json"
        ]
    },
    "totalTimeMs": 9454,
    "repairTimeMs": 459,
    "startTimeMs": 1613380759654,
    "crashes": [],
    "endTimeMs": 1613380769108,
    "parseTimeMs": 4445
}