{
    "repairs": [],
    "executionInfo": {
        "soraldVersion": "commit: 38248282",
        "javaVersion": "11.0.8",
        "originalArgs": [
            "repair",
            "--file-output-strategy",
            "IN_PLACE",
            "--original-files-path",
            "./",
            "--rule-keys",
            "2142",
            "--stats-output-file",
            "repair.json"
        ]
    },
    "totalTimeMs": 9209,
    "repairTimeMs": 230,
    "startTimeMs": 1613380715947,
    "crashes": [],
    "endTimeMs": 1613380725156,
    "parseTimeMs": 4320
}