{
    "repairs": [{
        "nbPerformedRepairs": 1,
        "ruleName": "UnclosedResources",
        "crashedRepairsLocations": [],
        "nbCrashedRepairs": 0,
        "ruleKey": "2095",
        "performedRepairsLocations": [{
            "endLine": 95,
            "endColumn": 35,
            "startColumn": 20,
            "startLine": 95,
            "filePath": "core/src/main/java/org/modelmapper/internal/Errors.java",
            "violationSpecifier": "2095:core/src/main/java/org/modelmapper/internal/Errors.java:95:20:95:35"
        }],
        "nbViolationsBefore": 1,
        "nbViolationsAfter": 0
    }],
    "executionInfo": {
        "soraldVersion": "commit: 38248282",
        "javaVersion": "11.0.8",
        "originalArgs": [
            "repair",
            "--file-output-strategy",
            "IN_PLACE",
            "--original-files-path",
            "./",
            "--rule-keys",
            "2095",
            "--stats-output-file",
            "repair.json"
        ]
    },
    "totalTimeMs": 14039,
    "repairTimeMs": 400,
    "startTimeMs": 1613320913673,
    "crashes": [],
    "endTimeMs": 1613320927712,
    "parseTimeMs": 4064
}