{
    "repairs": [{
        "nbPerformedRepairs": 23,
        "ruleName": "BigDecimalDoubleConstructor",
        "crashedRepairsLocations": [],
        "nbCrashedRepairs": 0,
        "ruleKey": "2111",
        "performedRepairsLocations": [
            {
                "endLine": 483,
                "endColumn": 41,
                "startColumn": 22,
                "filePath": "src/main/java/com/esri/core/geometry/Point2D.java",
                "startLine": 483,
                "violationSpecifier": "2111:src/main/java/com/esri/core/geometry/Point2D.java:483:22:483:41"
            },
            {
                "endLine": 484,
                "endColumn": 40,
                "startColumn": 21,
                "filePath": "src/main/java/com/esri/core/geometry/Point2D.java",
                "startLine": 484,
                "violationSpecifier": "2111:src/main/java/com/esri/core/geometry/Point2D.java:484:21:484:40"
            },
            {
                "endLine": 485,
                "endColumn": 40,
                "startColumn": 21,
                "filePath": "src/main/java/com/esri/core/geometry/Point2D.java",
                "startLine": 485,
                "violationSpecifier": "2111:src/main/java/com/esri/core/geometry/Point2D.java:485:21:485:40"
            },
            {
                "endLine": 488,
                "endColumn": 42,
                "startColumn": 23,
                "filePath": "src/main/java/com/esri/core/geometry/Point2D.java",
                "startLine": 488,
                "violationSpecifier": "2111:src/main/java/com/esri/core/geometry/Point2D.java:488:23:488:42"
            },
            {
                "endLine": 491,
                "endColumn": 42,
                "startColumn": 23,
                "filePath": "src/main/java/com/esri/core/geometry/Point2D.java",
                "startLine": 491,
                "violationSpecifier": "2111:src/main/java/com/esri/core/geometry/Point2D.java:491:23:491:42"
            },
            {
                "endLine": 494,
                "endColumn": 42,
                "startColumn": 23,
                "filePath": "src/main/java/com/esri/core/geometry/Point2D.java",
                "startLine": 494,
                "violationSpecifier": "2111:src/main/java/com/esri/core/geometry/Point2D.java:494:23:494:42"
            },
            {
                "endLine": 505,
                "endColumn": 40,
                "startColumn": 21,
                "filePath": "src/main/java/com/esri/core/geometry/Point2D.java",
                "startLine": 505,
                "violationSpecifier": "2111:src/main/java/com/esri/core/geometry/Point2D.java:505:21:505:40"
            },
            {
                "endLine": 505,
                "endColumn": 69,
                "startColumn": 50,
                "filePath": "src/main/java/com/esri/core/geometry/Point2D.java",
                "startLine": 505,
                "violationSpecifier": "2111:src/main/java/com/esri/core/geometry/Point2D.java:505:50:505:69"
            },
            {
                "endLine": 507,
                "endColumn": 41,
                "startColumn": 22,
                "filePath": "src/main/java/com/esri/core/geometry/Point2D.java",
                "startLine": 507,
                "violationSpecifier": "2111:src/main/java/com/esri/core/geometry/Point2D.java:507:22:507:41"
            },
            {
                "endLine": 507,
                "endColumn": 71,
                "startColumn": 52,
                "filePath": "src/main/java/com/esri/core/geometry/Point2D.java",
                "startLine": 507,
                "violationSpecifier": "2111:src/main/java/com/esri/core/geometry/Point2D.java:507:52:507:71"
            },
            {
                "endLine": 511,
                "endColumn": 41,
                "startColumn": 22,
                "filePath": "src/main/java/com/esri/core/geometry/Point2D.java",
                "startLine": 511,
                "violationSpecifier": "2111:src/main/java/com/esri/core/geometry/Point2D.java:511:22:511:41"
            },
            {
                "endLine": 511,
                "endColumn": 71,
                "startColumn": 52,
                "filePath": "src/main/java/com/esri/core/geometry/Point2D.java",
                "startLine": 511,
                "violationSpecifier": "2111:src/main/java/com/esri/core/geometry/Point2D.java:511:52:511:71"
            },
            {
                "endLine": 515,
                "endColumn": 41,
                "startColumn": 22,
                "filePath": "src/main/java/com/esri/core/geometry/Point2D.java",
                "startLine": 515,
                "violationSpecifier": "2111:src/main/java/com/esri/core/geometry/Point2D.java:515:22:515:41"
            },
            {
                "endLine": 515,
                "endColumn": 71,
                "startColumn": 52,
                "filePath": "src/main/java/com/esri/core/geometry/Point2D.java",
                "startLine": 515,
                "violationSpecifier": "2111:src/main/java/com/esri/core/geometry/Point2D.java:515:52:515:71"
            },
            {
                "endLine": 643,
                "endColumn": 45,
                "startColumn": 18,
                "filePath": "src/main/java/com/esri/core/geometry/Point2D.java",
                "startLine": 643,
                "violationSpecifier": "2111:src/main/java/com/esri/core/geometry/Point2D.java:643:18:643:45"
            },
            {
                "endLine": 644,
                "endColumn": 41,
                "startColumn": 19,
                "filePath": "src/main/java/com/esri/core/geometry/Point2D.java",
                "startLine": 644,
                "violationSpecifier": "2111:src/main/java/com/esri/core/geometry/Point2D.java:644:19:644:41"
            },
            {
                "endLine": 645,
                "endColumn": 45,
                "startColumn": 18,
                "filePath": "src/main/java/com/esri/core/geometry/Point2D.java",
                "startLine": 645,
                "violationSpecifier": "2111:src/main/java/com/esri/core/geometry/Point2D.java:645:18:645:45"
            },
            {
                "endLine": 646,
                "endColumn": 41,
                "startColumn": 19,
                "filePath": "src/main/java/com/esri/core/geometry/Point2D.java",
                "startLine": 646,
                "violationSpecifier": "2111:src/main/java/com/esri/core/geometry/Point2D.java:646:19:646:41"
            },
            {
                "endLine": 647,
                "endColumn": 38,
                "startColumn": 18,
                "filePath": "src/main/java/com/esri/core/geometry/Point2D.java",
                "startLine": 647,
                "violationSpecifier": "2111:src/main/java/com/esri/core/geometry/Point2D.java:647:18:647:38"
            },
            {
                "endLine": 648,
                "endColumn": 41,
                "startColumn": 19,
                "filePath": "src/main/java/com/esri/core/geometry/Point2D.java",
                "startLine": 648,
                "violationSpecifier": "2111:src/main/java/com/esri/core/geometry/Point2D.java:648:19:648:41"
            },
            {
                "endLine": 649,
                "endColumn": 38,
                "startColumn": 18,
                "filePath": "src/main/java/com/esri/core/geometry/Point2D.java",
                "startLine": 649,
                "violationSpecifier": "2111:src/main/java/com/esri/core/geometry/Point2D.java:649:18:649:38"
            },
            {
                "endLine": 650,
                "endColumn": 41,
                "startColumn": 19,
                "filePath": "src/main/java/com/esri/core/geometry/Point2D.java",
                "startLine": 650,
                "violationSpecifier": "2111:src/main/java/com/esri/core/geometry/Point2D.java:650:19:650:41"
            },
            {
                "endLine": 660,
                "endColumn": 36,
                "startColumn": 17,
                "filePath": "src/main/java/com/esri/core/geometry/Point2D.java",
                "startLine": 660,
                "violationSpecifier": "2111:src/main/java/com/esri/core/geometry/Point2D.java:660:17:660:36"
            }
        ],
        "nbViolationsBefore": 23,
        "nbViolationsAfter": 0
    }],
    "executionInfo": {
        "soraldVersion": "commit: 38248282",
        "javaVersion": "11.0.8",
        "originalArgs": [
            "repair",
            "--file-output-strategy",
            "IN_PLACE",
            "--original-files-path",
            "./",
            "--rule-keys",
            "2111",
            "--stats-output-file",
            "repair.json"
        ]
    },
    "totalTimeMs": 14718,
    "repairTimeMs": 898,
    "startTimeMs": 1613329952486,
    "crashes": [],
    "endTimeMs": 1613329967204,
    "parseTimeMs": 6824
}