{
    "repairs": [],
    "executionInfo": {
        "soraldVersion": "commit: ad3fdd7c",
        "javaVersion": "11.0.8",
        "originalArgs": [
            "repair",
            "--file-output-strategy",
            "IN_PLACE",
            "--original-files-path",
            "./",
            "--rule-keys",
            "2272",
            "--stats-output-file",
            "repair.json"
        ]
    },
    "totalTimeMs": 5896,
    "repairTimeMs": 336,
    "startTimeMs": 1612816344453,
    "crashes": [],
    "endTimeMs": 1612816350349,
    "parseTimeMs": 2794
}