{
    "repairs": [],
    "executionInfo": {
        "soraldVersion": "commit: 0c75eb6f",
        "javaVersion": "11.0.8",
        "originalArgs": [
            "repair",
            "--file-output-strategy",
            "IN_PLACE",
            "--original-files-path",
            "./",
            "--rule-keys",
            "1217",
            "--stats-output-file",
            "repair.json"
        ]
    },
    "totalTimeMs": 19202,
    "repairTimeMs": 831,
    "startTimeMs": 1610910313409,
    "crashes": [],
    "endTimeMs": 1610910332611,
    "parseTimeMs": 8763
}