{
    "repairs": [],
    "executionInfo": {
        "soraldVersion": "commit: 38248282",
        "javaVersion": "11.0.8",
        "originalArgs": [
            "repair",
            "--file-output-strategy",
            "IN_PLACE",
            "--original-files-path",
            "./",
            "--rule-keys",
            "2111",
            "--stats-output-file",
            "repair.json"
        ]
    },
    "totalTimeMs": 6158,
    "repairTimeMs": 261,
    "startTimeMs": 1613384289839,
    "crashes": [],
    "endTimeMs": 1613384295997,
    "parseTimeMs": 2502
}