{
    "repairs": [],
    "executionInfo": {
        "soraldVersion": "commit: 9a05e51b",
        "javaVersion": "11.0.8",
        "originalArgs": [
            "repair",
            "--file-output-strategy",
            "IN_PLACE",
            "--original-files-path",
            "./",
            "--rule-keys",
            "2142",
            "--stats-output-file",
            "repair.json"
        ]
    },
    "totalTimeMs": 6973,
    "repairTimeMs": 280,
    "startTimeMs": 1611593831639,
    "crashes": [],
    "endTimeMs": 1611593838612,
    "parseTimeMs": 3216
}