{
    "repairs": [],
    "executionInfo": {
        "soraldVersion": "commit: 38248282",
        "javaVersion": "11.0.8",
        "originalArgs": [
            "repair",
            "--file-output-strategy",
            "IN_PLACE",
            "--original-files-path",
            "./",
            "--rule-keys",
            "1217",
            "--stats-output-file",
            "repair.json"
        ]
    },
    "totalTimeMs": 2855,
    "repairTimeMs": 169,
    "startTimeMs": 1613350421649,
    "crashes": [],
    "endTimeMs": 1613350424504,
    "parseTimeMs": 920
}