{
    "repairs": [],
    "executionInfo": {
        "soraldVersion": "commit: ad3fdd7c",
        "javaVersion": "11.0.8",
        "originalArgs": [
            "repair",
            "--file-output-strategy",
            "IN_PLACE",
            "--original-files-path",
            "./",
            "--rule-keys",
            "4973",
            "--stats-output-file",
            "repair.json"
        ]
    },
    "totalTimeMs": 8479,
    "repairTimeMs": 408,
    "startTimeMs": 1612800388304,
    "crashes": [],
    "endTimeMs": 1612800396783,
    "parseTimeMs": 3676
}