{
    "repairs": [],
    "executionInfo": {
        "soraldVersion": "commit: 38248282",
        "javaVersion": "11.0.8",
        "originalArgs": [
            "repair",
            "--file-output-strategy",
            "IN_PLACE",
            "--original-files-path",
            "./",
            "--rule-keys",
            "2111",
            "--stats-output-file",
            "repair.json"
        ]
    },
    "totalTimeMs": 2858,
    "repairTimeMs": 129,
    "startTimeMs": 1613375666458,
    "crashes": [],
    "endTimeMs": 1613375669316,
    "parseTimeMs": 954
}