{
    "repairs": [],
    "executionInfo": {
        "soraldVersion": "commit: 38248282",
        "javaVersion": "11.0.8",
        "originalArgs": [
            "repair",
            "--file-output-strategy",
            "IN_PLACE",
            "--original-files-path",
            "./",
            "--rule-keys",
            "2116",
            "--stats-output-file",
            "repair.json"
        ]
    },
    "totalTimeMs": 16831,
    "repairTimeMs": 733,
    "startTimeMs": 1613329495301,
    "crashes": [],
    "endTimeMs": 1613329512132,
    "parseTimeMs": 7775
}